ricky_test_mcp_server/__init__.py
ricky_test_mcp_server-0.1.0.dist-info/WHEEL
ricky_test_mcp_server-0.1.0.dist-info/entry_points.txt
ricky_test_mcp_server-0.1.0.dist-info/METADATA
ricky_test_mcp_server-0.1.0.dist-info/RECORD
