Metadata-Version: 2.3
Name: ricky-test-mcp-server
Version: 0.1.0
Summary: Add your description here
Author: yikan
Author-email: yikan <yikanwang557@gmail.com>
Requires-Dist: mcp[cli]>=1.25.0
Requires-Python: >=3.13
